bu_cascade/__init__.py
bu_cascade/asset_tools.py
bu_cascade/cascade_connector.py
bu_cascade/assets/__init__.py
bu_cascade/assets/asset.py
bu_cascade/assets/block.py
bu_cascade/assets/data_definition.py
bu_cascade/assets/metadata_set.py
bu_cascade/assets/page.py
bu_cascade/exceptions/NoSuchTypeException.py
bu_cascade/exceptions/__init__.py
bu_cascade/utilities/__init__.py
bu_cascade/utilities/cache.py
bu_cascade-3.11.dist-info/METADATA
bu_cascade-3.11.dist-info/WHEEL
bu_cascade-3.11.dist-info/top_level.txt
bu_cascade-3.11.dist-info/RECORD
