Metadata-Version: 2.1
Name: bu-cascade
Version: 3.11
Summary: Cascade Server web services integration
Home-page: https://github.com/betheluniversity/cascade/
Author: Caleb Schwarze
Author-email: c-schwarze@bethel.edu
License: Apache 2.0
Platform: UNKNOWN
Requires-Dist: suds-jurko
Requires-Dist: beautifulsoup4
